valo_api_official/__init__.py
valo_api_official/config.py
valo_api_official/endpoints/__init__.py
valo_api_official/endpoints/account.py
valo_api_official/endpoints/active_shards.py
valo_api_official/endpoints/content.py
valo_api_official/endpoints/leaderboard.py
valo_api_official/endpoints/match_details.py
valo_api_official/endpoints/match_history.py
valo_api_official/endpoints/recent_matches.py
valo_api_official/endpoints/status.py
valo_api_official/endpoints_config.py
valo_api_official/exceptions/__init__.py
valo_api_official/exceptions/rate_limit.py
valo_api_official/exceptions/valo_api_exception.py
valo_api_official/responses/__init__.py
valo_api_official/responses/account.py
valo_api_official/responses/active_shards.py
valo_api_official/responses/content.py
valo_api_official/responses/error_response.py
valo_api_official/responses/leaderboard.py
valo_api_official/responses/match_details.py
valo_api_official/responses/match_history.py
valo_api_official/responses/recent_matches.py
valo_api_official/responses/status.py
valo_api_official/utils/__init__.py
valo_api_official/utils/fetch_endpoint.py
valo_api_official-1.0.1.dist-info/LICENSE
valo_api_official-1.0.1.dist-info/METADATA
valo_api_official-1.0.1.dist-info/WHEEL
valo_api_official-1.0.1.dist-info/RECORD
